BioFetcher/__init__.py
BioFetcher/downloader.py
scripts/__init__.py
scripts/run_downloader.py
BioFetcher-0.1.1.dist-info/LICENSE
BioFetcher-0.1.1.dist-info/METADATA
BioFetcher-0.1.1.dist-info/WHEEL
BioFetcher-0.1.1.dist-info/entry_points.txt
BioFetcher-0.1.1.dist-info/top_level.txt
BioFetcher-0.1.1.dist-info/RECORD
