Metadata-Version: 2.1
Name: BioFetcher
Version: 0.1.1
Summary: A package to download PDB and EMDB files and process protein/map data
Home-page: https://github.com/chenwei-zhang/BioFetcher.git
Author: Chenwei Zhang
Author-email: chwzhan@gmail.com
Classifier: Programming Language :: Python :: 3
Classifier: License :: OSI Approved :: GNU General Public License v3 (GPLv3)
Classifier: Operating System :: OS Independent
Requires-Python: >=3.6
License-File: LICENSE
Requires-Dist: requests
Requires-Dist: argparse
